{
    "name": "root",
    "metadata": {
        "timer_format_version": "0.1.0",
        "start_time_seconds": "1699025311",
        "python_version": "3.6.13 |Anaconda, Inc.| (default, Jun  4 2021, 14:25:59) \n[GCC 7.5.0]",
        "command_line_arguments": "/home/joshua/miniconda3/envs/ai_boat/bin/mlagents-learn config/boatAgent.yaml --run-id=kiteboat_20",
        "mlagents_version": "0.26.0",
        "mlagents_envs_version": "0.26.0",
        "communication_protocol_version": "1.5.0",
        "pytorch_version": "1.8.1+cu102",
        "numpy_version": "1.19.5",
        "end_time_seconds": "1699025318"
    },
    "total": 7.567587228000775,
    "count": 1,
    "self": 0.00530786600211286,
    "children": {
        "run_training.setup": {
            "total": 0.015642103000573115,
            "count": 1,
            "self": 0.015642103000573115
        },
        "TrainerController.start_learning": {
            "total": 7.546637258998089,
            "count": 1,
            "self": 0.00024021600256673992,
            "children": {
                "TrainerController._reset_env": {
                    "total": 7.546388176997425,
                    "count": 1,
                    "self": 7.546388176997425
                },
                "trainer_threads": {
                    "total": 1.3699973351322114e-06,
                    "count": 1,
                    "self": 1.3699973351322114e-06
                },
                "TrainerController._save_models": {
                    "total": 7.496000762330368e-06,
                    "count": 1,
                    "self": 7.496000762330368e-06
                }
            }
        }
    }
}